mediqaws/clients/__init__.py
mediqaws/clients/abc.py
mediqaws/clients/kms.py
mediqaws/clients/s3.py
mediqaws/clients/ses.py
mediqaws/clients/sns.py
mediqaws/clients/sqs.py
mediqaws/secrets_manager/__init__.py
mediqaws-0.0.6.dist-info/LICENSE
mediqaws-0.0.6.dist-info/METADATA
mediqaws-0.0.6.dist-info/WHEEL
mediqaws-0.0.6.dist-info/top_level.txt
mediqaws-0.0.6.dist-info/RECORD
