Metadata-Version: 2.2
Name: mediqaws
Version: 0.0.6
Summary: A collection of AWS clients, and a secrets manager.
Home-page: https://github.com/SmartMediQ/mediqaws
Author: Smartmediq
Author-email: dev@smartmediq.com
Classifier: Operating System :: OS Independent
Classifier: Programming Language :: Python :: 3
Classifier: Programming Language :: Python :: 3.11
Classifier: Programming Language :: Python :: 3.12
Classifier: Topic :: Scientific/Engineering :: Medical Science Apps.
Classifier: Topic :: Software Development :: Libraries :: Python Modules
Requires-Python: >=3.11
License-File: LICENSE
Requires-Dist: boto3
Requires-Dist: pydantic
Requires-Dist: werkzeug
Dynamic: author
Dynamic: author-email
Dynamic: classifier
Dynamic: description
Dynamic: description-content-type
Dynamic: home-page
Dynamic: requires-dist
Dynamic: requires-python
Dynamic: summary
